speckle_pattern/__init__.py
speckle_pattern/speckle.py
speckle_pattern-1.3.3.dist-info/METADATA
speckle_pattern-1.3.3.dist-info/WHEEL
speckle_pattern-1.3.3.dist-info/licenses/LICENSE
speckle_pattern-1.3.3.dist-info/RECORD
