Metadata-Version: 2.3
Name: speckle_pattern
Version: 1.3.3
Summary: Generate print-ready pattern images for DIC applications.
Project-URL: Homepage, https://github.com/ladisk/speckle_pattern
Project-URL: Bug Tracker, https://github.com/ladisk/speckle_pattern/issues
Author-email: "Domen Gorjup, Janko Slavič, Miha Boltežar" <janko.slavic@fs.uni-lj.si>
License-Expression: MIT
License-File: LICENSE
Keywords: computer vision,dic,speckle pattern
Classifier: Development Status :: 5 - Production/Stable
Classifier: Intended Audience :: Developers
Classifier: License :: OSI Approved :: MIT License
Classifier: Programming Language :: Python :: 3.10
Classifier: Topic :: Scientific/Engineering
Requires-Python: >=3.10
Requires-Dist: imageio>=2.2.0
Requires-Dist: matplotlib>=2.0.0
Requires-Dist: numpy>=1.0.0
Requires-Dist: piexif>=1.0.13
Requires-Dist: scipy>=1.0.0
Requires-Dist: tqdm>=4.10.0
